aleph_alpha_client/__init__.py
aleph_alpha_client/aleph_alpha_client.py
aleph_alpha_client/chat.py
aleph_alpha_client/completion.py
aleph_alpha_client/detokenization.py
aleph_alpha_client/document.py
aleph_alpha_client/embedding.py
aleph_alpha_client/evaluation.py
aleph_alpha_client/explanation.py
aleph_alpha_client/prompt.py
aleph_alpha_client/prompt_template.py
aleph_alpha_client/py.typed
aleph_alpha_client/reranking.py
aleph_alpha_client/steering.py
aleph_alpha_client/structured_output.py
aleph_alpha_client/tokenization.py
aleph_alpha_client/translation.py
aleph_alpha_client/utils.py
aleph_alpha_client/version.py
aleph_alpha_client-11.5.1.dist-info/licenses/LICENSE
aleph_alpha_client-11.5.1.dist-info/METADATA
aleph_alpha_client-11.5.1.dist-info/WHEEL
aleph_alpha_client-11.5.1.dist-info/top_level.txt
aleph_alpha_client-11.5.1.dist-info/RECORD
