Metadata-Version: 2.4
Name: aleph-alpha-client
Version: 11.5.1
Summary: python client to interact with Aleph Alpha api endpoints
Author-email: Aleph Alpha <support@aleph-alpha.com>
License-Expression: MIT
Project-URL: Homepage, https://github.com/Aleph-Alpha/aleph-alpha-client
Requires-Python: <3.14,>=3.10
License-File: LICENSE
Requires-Dist: requests>=2.28
Requires-Dist: urllib3>=1.26
Requires-Dist: aiohttp>=3.10.2
Requires-Dist: aiodns>=3.2.0
Requires-Dist: aiohttp-retry>=2.8.3
Requires-Dist: tokenizers>=0.13.2
Requires-Dist: typing-extensions>=4.5.0
Requires-Dist: Pillow>=9.2.0
Requires-Dist: tqdm>=4.62.0
Requires-Dist: python-liquid!=2.0.2,>=1.9.4
Requires-Dist: packaging>=23.2
Requires-Dist: pydantic
Dynamic: license-file
